Metadata-Version: 2.1
Name: splittercalculationlibrary
Version: 0.1.0
Summary: A simple calculation for the Splitwise application
Home-page: UNKNOWN
Author: Soorya
Author-email: jeyasooryamanoharan@gmail.com
License: UNKNOWN
Keywords: splittercalculation
Platform: UNKNOWN
Classifier: Development Status :: 3 - Alpha
Classifier: Programming Language :: Python :: 3
Classifier: License :: OSI Approved :: MIT License
Classifier: Operating System :: OS Independent
Requires-Python: >=3.6
